pykinect_recorder/__init__.py
pykinect_recorder/cli/__init__.py
pykinect_recorder/cli/command.py
pykinect_recorder/main_window.py
pykinect_recorder/pyk4a/__init__.py
pykinect_recorder/pyk4a/k4a/__init__.py
pykinect_recorder/pyk4a/k4a/_k4a.py
pykinect_recorder/pyk4a/k4a/_k4atypes.py
pykinect_recorder/pyk4a/k4a/calibration.py
pykinect_recorder/pyk4a/k4a/capture.py
pykinect_recorder/pyk4a/k4a/configuration.py
pykinect_recorder/pyk4a/k4a/device.py
pykinect_recorder/pyk4a/k4a/image.py
pykinect_recorder/pyk4a/k4a/imu_sample.py
pykinect_recorder/pyk4a/k4a/transformation.py
pykinect_recorder/pyk4a/k4abt/__init__.py
pykinect_recorder/pyk4a/k4abt/_k4abt.py
pykinect_recorder/pyk4a/k4abt/_k4abtTypes.py
pykinect_recorder/pyk4a/k4abt/body.py
pykinect_recorder/pyk4a/k4abt/body2d.py
pykinect_recorder/pyk4a/k4abt/frame.py
pykinect_recorder/pyk4a/k4abt/joint.py
pykinect_recorder/pyk4a/k4abt/joint2d.py
pykinect_recorder/pyk4a/k4abt/tracker.py
pykinect_recorder/pyk4a/k4arecord/__init__.py
pykinect_recorder/pyk4a/k4arecord/_k4arecord.py
pykinect_recorder/pyk4a/k4arecord/_k4arecordTypes.py
pykinect_recorder/pyk4a/k4arecord/datablock.py
pykinect_recorder/pyk4a/k4arecord/playback.py
pykinect_recorder/pyk4a/k4arecord/record.py
pykinect_recorder/pyk4a/k4arecord/record_configuration.py
pykinect_recorder/pyk4a/pykinect.py
pykinect_recorder/pyk4a/utils.py
pykinect_recorder/pyrealsense/__init__.py
pykinect_recorder/pyzenmuse/__init__.py
pykinect_recorder/renderer/__init__.py
pykinect_recorder/renderer/common_widgets.py
pykinect_recorder/renderer/components/__init__.py
pykinect_recorder/renderer/components/playback_sensors.py
pykinect_recorder/renderer/components/record_sensors.py
pykinect_recorder/renderer/components/sidebar_control.py
pykinect_recorder/renderer/components/sidebar_explorer.py
pykinect_recorder/renderer/components/sidebar_menu.py
pykinect_recorder/renderer/components/sidebar_record_control.py
pykinect_recorder/renderer/components/sidebar_solutions.py
pykinect_recorder-0.9.4.dist-info/entry_points.txt
pykinect_recorder-0.9.4.dist-info/LICENSE
pykinect_recorder-0.9.4.dist-info/METADATA
pykinect_recorder-0.9.4.dist-info/WHEEL
pykinect_recorder-0.9.4.dist-info/RECORD
